odoo/addons/pos_pms_link/README.rst
odoo/addons/pos_pms_link/__init__.py
odoo/addons/pos_pms_link/__manifest__.py
odoo/addons/pos_pms_link/i18n/de.po
odoo/addons/pos_pms_link/i18n/es.po
odoo/addons/pos_pms_link/i18n/it.po
odoo/addons/pos_pms_link/i18n/pos_pms_link.pot
odoo/addons/pos_pms_link/models/__init__.py
odoo/addons/pos_pms_link/models/pms_reservation.py
odoo/addons/pos_pms_link/models/pms_service.py
odoo/addons/pos_pms_link/models/pms_service_line.py
odoo/addons/pos_pms_link/models/pos_config.py
odoo/addons/pos_pms_link/models/pos_order.py
odoo/addons/pos_pms_link/models/pos_payment.py
odoo/addons/pos_pms_link/models/pos_session.py
odoo/addons/pos_pms_link/models/product_pricelist.py
odoo/addons/pos_pms_link/models/res_config_settings.py
odoo/addons/pos_pms_link/models/res_partner.py
odoo/addons/pos_pms_link/static/description/icon.png
odoo/addons/pos_pms_link/static/src/js/CashOpeningPopup.esm.js
odoo/addons/pos_pms_link/static/src/js/ReservationSelectionButton.esm.js
odoo/addons/pos_pms_link/static/src/js/db.esm.js
odoo/addons/pos_pms_link/static/src/js/models.esm.js
odoo/addons/pos_pms_link/static/src/js/Popups/CashMovePopup.esm.js
odoo/addons/pos_pms_link/static/src/js/Popups/ClosePosPopup.esm.js
odoo/addons/pos_pms_link/static/src/js/Popups/PartnerListPopup.esm.js
odoo/addons/pos_pms_link/static/src/js/Screens/ChromeWidgets/CashMoveButton.esm.js
odoo/addons/pos_pms_link/static/src/js/Screens/ChromeWidgets/Chrome.esm.js
odoo/addons/pos_pms_link/static/src/js/Screens/PaymentScreen/PaymentScreen.esm.js
odoo/addons/pos_pms_link/static/src/js/Screens/ReceiptScreen/OrderReceipt.esm.js
odoo/addons/pos_pms_link/static/src/js/Screens/ReservationListScreen/ReservationDetailsEdit.esm.js
odoo/addons/pos_pms_link/static/src/js/Screens/ReservationListScreen/ReservationLine.esm.js
odoo/addons/pos_pms_link/static/src/js/Screens/ReservationListScreen/ReservationListScreen.esm.js
odoo/addons/pos_pms_link/static/src/scss/partner_popup.scss
odoo_addon_pos_pms_link-16.0.1.0.0.6.dist-info/METADATA
odoo_addon_pos_pms_link-16.0.1.0.0.6.dist-info/WHEEL
odoo_addon_pos_pms_link-16.0.1.0.0.6.dist-info/top_level.txt
odoo_addon_pos_pms_link-16.0.1.0.0.6.dist-info/RECORD
